<?xml version="1.0" encoding="UTF-8" standalone="yes"?><jejunetApi><error>false</error><result>SUCCESS</result><resultCode>00</resultCode><resultMsg>success</resultMsg><items><item><type>원문</type><codeNo>T_M_032</codeNo><category>신화</category><category2>MYTH2.002</category2><ebook>T_M_032</ebook><ebookUrl>http://www.jeju.go.kr/pub/site/cul/ebook/001/1926/T_M_032/e-book.html</ebookUrl><title>사계본향 큰물당</title><tag>사계본향 큰물당</tag><pdf>T_M_032.pdf</pdf><pdfUrl>http://www.jeju.go.kr/files/board/1f5a7ddc-4f93-455d-a4ed-bf768178b8bc.pdf</pdfUrl></item><item><type>원문</type><codeNo>T_M_033</codeNo><category>신화</category><category2>MYTH2.001</category2><ebook>T_M_033</ebook><ebookUrl>http://www.jeju.go.kr/pub/site/cul/ebook/001/1926/T_M_033/e-book.html</ebookUrl><title>삼공본풀이</title><tag>본풀이,삼공본풀이</tag><pdf>T_M_033.pdf</pdf><pdfUrl>http://www.jeju.go.kr/files/board/7a5c8528-f24d-4ba8-8974-605813aec839.pdf</pdfUrl></item></items><query><pageSize>2</pageSize><page>19</page><rows>182</rows></query></jejunetApi>