<?xml version="1.0" encoding="UTF-8" standalone="yes"?><jejunetApi><error>false</error><result>SUCCESS</result><resultCode>00</resultCode><resultMsg>success</resultMsg><items><item><type>원문</type><codeNo>T_F_001</codeNo><category>민담</category><category2>MYTH2.015</category2><ebook>T_F_001</ebook><ebookUrl>http://www.jeju.go.kr/pub/site/cul/ebook/001/1928/T_F_001/e-book.html</ebookUrl><title>개와 닭의 원한</title><tag>개,닭,원한</tag><pdf>T_F_001.pdf</pdf><pdfUrl>http://www.jeju.go.kr/files/board/d1194379-0c99-4eee-b5be-02aeec232de9.pdf</pdfUrl></item><item><type>원문</type><codeNo>T_F_002</codeNo><category>민담</category><category2>MYTH2.015</category2><ebook>T_F_002</ebook><ebookUrl>http://www.jeju.go.kr/pub/site/cul/ebook/001/1928/T_F_002/e-book.html</ebookUrl><title>겸손을 배운 제자</title><tag>겸손,제자</tag><pdf>T_F_002.pdf</pdf><pdfUrl>http://www.jeju.go.kr/files/board/8a122871-ffe9-432f-8095-0d66cc402a1b.pdf</pdfUrl></item><item><type>원문</type><codeNo>T_F_003</codeNo><category>민담</category><category2>MYTH2.015</category2><ebook>T_F_003</ebook><ebookUrl>http://www.jeju.go.kr/pub/site/cul/ebook/001/1928/T_F_003/e-book.html</ebookUrl><title>계모의 모략(1)</title><tag>계모,모략</tag><pdf>T_F_003.pdf</pdf><pdfUrl>http://www.jeju.go.kr/files/board/10f743e4-5230-4d94-b60b-cf08bd8d3133.pdf</pdfUrl></item><item><type>원문</type><codeNo>T_F_004</codeNo><category>민담</category><category2>MYTH2.015</category2><ebook>T_F_004</ebook><ebookUrl>http://www.jeju.go.kr/pub/site/cul/ebook/001/1928/T_F_004/e-book.html</ebookUrl><title>과거보는 선비 이야기</title><tag>과거,선비</tag><pdf>T_F_004.pdf</pdf><pdfUrl>http://www.jeju.go.kr/files/board/7fa63de3-f01c-49cb-b0cb-96f8c8a01ccc.pdf</pdfUrl></item><item><type>원문</type><codeNo>T_F_005</codeNo><category>민담</category><category2>MYTH2.015</category2><ebook>T_F_005</ebook><ebookUrl>http://www.jeju.go.kr/pub/site/cul/ebook/001/1928/T_F_005/e-book.html</ebookUrl><title>괴상한 세 동무</title><tag>동무</tag><pdf>T_F_005.pdf</pdf><pdfUrl>http://www.jeju.go.kr/files/board/822fba8e-2e6a-4878-82c4-b5f34b5e1d86.pdf</pdfUrl></item><item><type>원문</type><codeNo>T_F_006</codeNo><category>민담</category><category2>MYTH2.016</category2><ebook>T_F_006</ebook><ebookUrl>http://www.jeju.go.kr/pub/site/cul/ebook/001/1928/T_F_006/e-book.html</ebookUrl><title>구렁이가 된 막내</title><tag>구렁이,막내</tag><pdf>T_F_006.pdf</pdf><pdfUrl>http://www.jeju.go.kr/files/board/27f551f7-e172-4426-8165-e4e91d770b40.pdf</pdfUrl></item><item><type>원문</type><codeNo>T_F_007</codeNo><category>민담</category><category2>MYTH2.015</category2><ebook>T_F_007</ebook><ebookUrl>http://www.jeju.go.kr/pub/site/cul/ebook/001/1928/T_F_007/e-book.html</ebookUrl><title>귀신대2</title><tag>귀신대</tag><pdf>T_F_007.pdf</pdf><pdfUrl>http://www.jeju.go.kr/files/board/96fb8c50-32fa-4315-995a-dd9999364cfb.pdf</pdfUrl></item><item><type>원문</type><codeNo>T_F_008</codeNo><category>민담</category><category2>MYTH2.014</category2><ebook>T_F_008</ebook><ebookUrl>http://www.jeju.go.kr/pub/site/cul/ebook/001/1928/T_F_008/e-book.html</ebookUrl><title>말 한마디로 복 얻은 노인</title><tag>말,노인,복</tag><pdf>T_F_008.pdf</pdf><pdfUrl>http://www.jeju.go.kr/files/board/438c1344-cb42-465a-9403-ac3167c6e94e.pdf</pdfUrl></item><item><type>원문</type><codeNo>T_F_009</codeNo><category>민담</category><category2>MYTH2.016</category2><ebook>T_F_009</ebook><ebookUrl>http://www.jeju.go.kr/pub/site/cul/ebook/001/1928/T_F_009/e-book.html</ebookUrl><title>말(馬)이야기</title><tag>말</tag><pdf>T_F_009.pdf</pdf><pdfUrl>http://www.jeju.go.kr/files/board/20d6e439-8b51-46d9-98e8-bcd51432acb3.pdf</pdfUrl></item><item><type>원문</type><codeNo>T_F_010</codeNo><category>민담</category><category2>MYTH2.016</category2><ebook>T_F_010</ebook><ebookUrl>http://www.jeju.go.kr/pub/site/cul/ebook/001/1928/T_F_010/e-book.html</ebookUrl><title>멜잡는 도채비</title><tag>도채비,멜</tag><pdf>T_F_010.pdf</pdf><pdfUrl>http://www.jeju.go.kr/files/board/6120bf6c-0b2f-44fa-a1e7-26632b516d5d.pdf</pdfUrl></item><item><type>원문</type><codeNo>T_F_011</codeNo><category>민담</category><category2>MYTH2.014</category2><ebook>T_F_011</ebook><ebookUrl>http://www.jeju.go.kr/pub/site/cul/ebook/001/1928/T_F_011/e-book.html</ebookUrl><title>사름 아니라는 욕</title><tag>사름,욕</tag><pdf>T_F_011.pdf</pdf><pdfUrl>http://www.jeju.go.kr/files/board/9de1749b-fdb6-4379-93a4-ef33c2866849.pdf</pdfUrl></item><item><type>원문</type><codeNo>T_F_012</codeNo><category>민담</category><category2>MYTH2.016</category2><ebook>T_F_012</ebook><ebookUrl>http://www.jeju.go.kr/pub/site/cul/ebook/001/1928/T_F_012/e-book.html</ebookUrl><title>산도채비</title><tag>도채비,산도채비</tag><pdf>T_F_012.pdf</pdf><pdfUrl>http://www.jeju.go.kr/files/board/924bc2e9-5612-4441-99a3-a9bea188f904.pdf</pdfUrl></item><item><type>원문</type><codeNo>T_F_013</codeNo><category>민담</category><category2>MYTH2.014</category2><ebook>T_F_013</ebook><ebookUrl>http://www.jeju.go.kr/pub/site/cul/ebook/001/1928/T_F_013/e-book.html</ebookUrl><title>신기한 호랑이 눈썹</title><tag>호랑이,눈썹</tag><pdf>T_F_013.pdf</pdf><pdfUrl>http://www.jeju.go.kr/files/board/ef98bac4-f0f1-42fe-ae6c-66be50254684.pdf</pdfUrl></item><item><type>현지조사</type><codeNo>W_F_001</codeNo><category>민담</category><category2>MYTH2.016</category2><ebook>W_F_001</ebook><ebookUrl>http://www.jeju.go.kr/pub/site/cul/ebook/003/1928/W_F_001/e-book.html</ebookUrl><title>가파도 도체비와 영장</title><tag>도체비,영장,가파도,헛불</tag><pdf>W_F_001.pdf</pdf><pdfUrl>http://www.jeju.go.kr/files/board/757a72ff-f810-4cf0-9d26-8bfffda4d09a.pdf</pdfUrl></item><item><type>현지조사</type><codeNo>W_F_002</codeNo><category>민담</category><category2>MYTH2.015</category2><ebook>W_F_002</ebook><ebookUrl>http://www.jeju.go.kr/pub/site/cul/ebook/003/1928/W_F_002/e-book.html</ebookUrl><title>각시 셋 헌 정승</title><tag>각시,정승,장개,일정승,이정승,삼정승</tag><pdf>W_F_002.pdf</pdf><pdfUrl>http://www.jeju.go.kr/files/board/53b5db73-e279-4ba8-9fd5-aa79502136ca.pdf</pdfUrl></item><item><type>현지조사</type><codeNo>W_F_003</codeNo><category>민담</category><category2>MYTH2.016</category2><ebook>W_F_003</ebook><ebookUrl>http://www.jeju.go.kr/pub/site/cul/ebook/003/1928/W_F_003/e-book.html</ebookUrl><title>갈치와 도체비</title><tag>도체비,식게,갈치,당낭밧,제숙,불난디</tag><pdf>W_F_003.pdf</pdf><pdfUrl>http://www.jeju.go.kr/files/board/5161c2bf-6352-4660-b500-6ac49d286619.pdf</pdfUrl></item><item><type>현지조사</type><codeNo>W_F_004</codeNo><category>민담</category><category2>MYTH2.016</category2><ebook>W_F_004</ebook><ebookUrl>http://www.jeju.go.kr/pub/site/cul/ebook/003/1928/W_F_004/e-book.html</ebookUrl><title>고산리 도체빗불</title><tag>도체비,도체빗불,고산리,녹고물,매고무동산,사람조름,한경면고산리</tag><pdf>W_F_004.pdf</pdf><pdfUrl>http://www.jeju.go.kr/files/board/ea61debc-546d-44ac-a66d-ee26e20078f8.pdf</pdfUrl></item><item><type>현지조사</type><codeNo>W_F_005</codeNo><category>민담</category><category2>MYTH2.015</category2><ebook>W_F_005</ebook><ebookUrl>http://www.jeju.go.kr/pub/site/cul/ebook/003/1928/W_F_005/e-book.html</ebookUrl><title>과부와 심방</title><tag>심방,무덤,과부,부채,선제</tag><pdf>W_F_005.pdf</pdf><pdfUrl>http://www.jeju.go.kr/files/board/66d7b1cc-7f8b-4933-9447-b65892c0cb6d.pdf</pdfUrl></item><item><type>현지조사</type><codeNo>W_F_006</codeNo><category>민담</category><category2>MYTH2.016</category2><ebook>W_F_006</ebook><ebookUrl>http://www.jeju.go.kr/pub/site/cul/ebook/003/1928/W_F_006/e-book.html</ebookUrl><title>그슨대</title><tag>구신,마,강알,소곰막,그슨대,오월장마,잘,나는,날씨,왁왁,크등한거,휏불</tag><pdf>W_F_006.pdf</pdf><pdfUrl>http://www.jeju.go.kr/files/board/0973d0dc-e99e-43a1-a37a-e2a7ecd464c3.pdf</pdfUrl></item><item><type>현지조사</type><codeNo>W_F_007</codeNo><category>민담</category><category2>MYTH2.015</category2><ebook>W_F_007</ebook><ebookUrl>http://www.jeju.go.kr/pub/site/cul/ebook/003/1928/W_F_007/e-book.html</ebookUrl><title>꿩 잡앙 망헌 집</title><tag>집,쌀,꿩,성제,도독질,도세기막,통쉐</tag><pdf>W_F_007.pdf</pdf><pdfUrl>http://www.jeju.go.kr/files/board/7af4177f-e212-4370-8bd4-fdeb6d454e66.pdf</pdfUrl></item><item><type>현지조사</type><codeNo>W_F_008</codeNo><category>민담</category><category2>MYTH2.016</category2><ebook>W_F_008</ebook><ebookUrl>http://www.jeju.go.kr/pub/site/cul/ebook/003/1928/W_F_008/e-book.html</ebookUrl><title>날아다니는 전복</title><tag>전복,추자도,풍선,강진,범선,해남,조업</tag><pdf>W_F_008.pdf</pdf><pdfUrl>http://www.jeju.go.kr/files/board/c595e785-a2d2-4f69-8c32-677fdb954fd0.pdf</pdfUrl></item><item><type>현지조사</type><codeNo>W_F_009</codeNo><category>민담</category><category2>MYTH2.015</category2><ebook>W_F_009</ebook><ebookUrl>http://www.jeju.go.kr/pub/site/cul/ebook/003/1928/W_F_009/e-book.html</ebookUrl><title>남선비</title><tag>할망,남선비,일곱성제,족은각시,큰각시,애,아덜,산토세기</tag><pdf>W_F_009.pdf</pdf><pdfUrl>http://www.jeju.go.kr/files/board/ed9a6e8a-056c-4326-b09f-5ba532cdabd7.pdf</pdfUrl></item><item><type>현지조사</type><codeNo>W_F_010</codeNo><category>민담</category><category2>MYTH2.016</category2><ebook>W_F_010</ebook><ebookUrl>http://www.jeju.go.kr/pub/site/cul/ebook/003/1928/W_F_010/e-book.html</ebookUrl><title>낮도체비</title><tag>도체비,헛게,사금바치,불난지불,낮도체비,벤장,사람홀리기,냇돌</tag><pdf>W_F_010.pdf</pdf><pdfUrl>http://www.jeju.go.kr/files/board/c3921a22-3785-4305-9645-2246ad6fa071.pdf</pdfUrl></item><item><type>현지조사</type><codeNo>W_F_011</codeNo><category>민담</category><category2>MYTH2.016</category2><ebook>W_F_011</ebook><ebookUrl>http://www.jeju.go.kr/pub/site/cul/ebook/003/1928/W_F_011/e-book.html</ebookUrl><title>도깨비 조상과 도깨빗불</title><tag>도깨비,불,비,조상,도깨빗불,헛게비,우는소리,도깨비불,웃봉,비차락,얼레기빗,척척한날,밤질,도깨비 조상</tag><pdf>W_F_011.pdf</pdf><pdfUrl>http://www.jeju.go.kr/files/board/0d7b2af9-7aed-403e-a8e1-35f525d4100a.pdf</pdfUrl></item><item><type>현지조사</type><codeNo>W_F_012</codeNo><category>민담</category><category2>MYTH2.015</category2><ebook>W_F_012</ebook><ebookUrl>http://www.jeju.go.kr/pub/site/cul/ebook/003/1928/W_F_012/e-book.html</ebookUrl><title>도깨비 행세 헷당 원수 뒌 사위</title><tag>도깨비,종달리,구신,사위,구좌읍종달리,수수범벅,장모,원수</tag><pdf>W_F_012.pdf</pdf><pdfUrl>http://www.jeju.go.kr/files/board/a5689c7c-daeb-4c01-a1ec-f5090847e995.pdf</pdfUrl></item><item><type>현지조사</type><codeNo>W_F_013</codeNo><category>민담</category><category2>MYTH2.016</category2><ebook>W_F_013</ebook><ebookUrl>http://www.jeju.go.kr/pub/site/cul/ebook/003/1928/W_F_013/e-book.html</ebookUrl><title>도깨비와 친구</title><tag>도깨비,불,구신,각시,친구,구좌읍덕천리,원숭이</tag><pdf>W_F_013.pdf</pdf><pdfUrl>http://www.jeju.go.kr/files/board/99a115cd-b4c5-455b-ae8d-f7105daa4350.pdf</pdfUrl></item><item><type>현지조사</type><codeNo>W_F_014</codeNo><category>민담</category><category2>MYTH2.016</category2><ebook>W_F_014</ebook><ebookUrl>http://www.jeju.go.kr/pub/site/cul/ebook/003/1928/W_F_014/e-book.html</ebookUrl><title>도체빗불 줍젠 허당 물에 빠진 하르방</title><tag>하르방,물,소,도체빗불,물하르방</tag><pdf>W_F_014.pdf</pdf><pdfUrl>http://www.jeju.go.kr/files/board/95e7257c-62b5-4143-9691-acc3b22a6596.pdf</pdfUrl></item><item><type>현지조사</type><codeNo>W_F_015</codeNo><category>민담</category><category2>MYTH2.016</category2><ebook>W_F_015</ebook><ebookUrl>http://www.jeju.go.kr/pub/site/cul/ebook/003/1928/W_F_015/e-book.html</ebookUrl><title>도체비와 도독놈</title><tag>도체비,소금,시흥리,구좌읍종달리,사둔,도둑놈,도독</tag><pdf>W_F_015.pdf</pdf><pdfUrl>http://www.jeju.go.kr/files/board/ac38e9c3-4591-41f5-b426-b9c381e73e0d.pdf</pdfUrl></item><item><type>현지조사</type><codeNo>W_F_016</codeNo><category>민담</category><category2>MYTH2.016</category2><ebook>W_F_016</ebook><ebookUrl>http://www.jeju.go.kr/pub/site/cul/ebook/003/1928/W_F_016/e-book.html</ebookUrl><title>도체비와 해월스님</title><tag>도체비,불,팥죽,천지대양교,해월스님</tag><pdf>W_F_016.pdf</pdf><pdfUrl>http://www.jeju.go.kr/files/board/95c98a5b-4fdc-4727-bd71-7ca8f4150422.pdf</pdfUrl></item><item><type>현지조사</type><codeNo>W_F_017</codeNo><category>민담</category><category2>MYTH2.016</category2><ebook>W_F_017</ebook><ebookUrl>http://www.jeju.go.kr/pub/site/cul/ebook/003/1928/W_F_017/e-book.html</ebookUrl><title>도체빗불</title><tag>돌,도체빗불,상도리,멘수동,안모살동네,쒜돈</tag><pdf>W_F_017.pdf</pdf><pdfUrl>http://www.jeju.go.kr/files/board/9eac2f17-2194-4a0f-84b5-631f91c424d3.pdf</pdfUrl></item><item><type>현지조사</type><codeNo>W_F_018</codeNo><category>민담</category><category2>MYTH2.016</category2><ebook>W_F_018</ebook><ebookUrl>http://www.jeju.go.kr/pub/site/cul/ebook/003/1928/W_F_018/e-book.html</ebookUrl><title>뒈지고기와 도체비</title><tag>도체비,하르방,뒈지고기,표선면가시리,영아리</tag><pdf>W_F_018.pdf</pdf><pdfUrl>http://www.jeju.go.kr/files/board/3840a520-6a3f-42b3-afe0-b6466bb0b2e0.pdf</pdfUrl></item><item><type>현지조사</type><codeNo>W_F_019</codeNo><category>민담</category><category2>MYTH2.016</category2><ebook>W_F_019</ebook><ebookUrl>http://www.jeju.go.kr/pub/site/cul/ebook/003/1928/W_F_019/e-book.html</ebookUrl><title>따라비오름 상여소리</title><tag>도체빗불,헛게,천리,따라비오름,영장메가는소리,팔롱팔롱,불란지,상여소리</tag><pdf>W_F_019.pdf</pdf><pdfUrl>http://www.jeju.go.kr/files/board/e58f2bf6-ee72-4825-a6b6-1c7628bc62d3.pdf</pdfUrl></item><item><type>현지조사</type><codeNo>W_F_020</codeNo><category>민담</category><category2>MYTH2.016</category2><ebook>W_F_020</ebook><ebookUrl>http://www.jeju.go.kr/pub/site/cul/ebook/003/1928/W_F_020/e-book.html</ebookUrl><title>멜 들엇덴 *골아주는 도체비</title><tag>도체비,개,바다,멜,돌담,구좌읍행원리</tag><pdf>W_F_020.pdf</pdf><pdfUrl>http://www.jeju.go.kr/files/board/aa56a945-a3bf-4125-b0a9-380a6a40f8ec.pdf</pdfUrl></item><item><type>현지조사</type><codeNo>W_F_021</codeNo><category>민담</category><category2>MYTH2.015</category2><ebook>W_F_021</ebook><ebookUrl>http://www.jeju.go.kr/pub/site/cul/ebook/003/1928/W_F_021/e-book.html</ebookUrl><title>물 *한번 질레 가느니 아기를 나비켜</title><tag>물,할망,아기,힘쎈할망,홍여옥할망,물질기,아기낳기</tag><pdf>W_F_021.pdf</pdf><pdfUrl>http://www.jeju.go.kr/files/board/187bc852-b452-4a58-8ca9-ada050480d0c.pdf</pdfUrl></item><item><type>현지조사</type><codeNo>W_F_022</codeNo><category>민담</category><category2>MYTH2.018</category2><ebook>W_F_022</ebook><ebookUrl>http://www.jeju.go.kr/pub/site/cul/ebook/003/1928/W_F_022/e-book.html</ebookUrl><title>바당에서 죽은 신산리 아홉 동서</title><tag>바당,신산리,성산읍신산리,아홉동서,덕판,폭풍</tag><pdf>W_F_022.pdf</pdf><pdfUrl>http://www.jeju.go.kr/files/board/2f75438d-9c51-468b-ab9a-4febe266224a.pdf</pdfUrl></item><item><type>현지조사</type><codeNo>W_F_023</codeNo><category>민담</category><category2>MYTH2.017</category2><ebook>W_F_023</ebook><ebookUrl>http://www.jeju.go.kr/pub/site/cul/ebook/003/1928/W_F_023/e-book.html</ebookUrl><title>버버리 할망과 봉사 하르방</title><tag>하르방,불,할망,봉사,버버리,버버리 할망,봉사 하르방</tag><pdf>W_F_023.pdf</pdf><pdfUrl>http://www.jeju.go.kr/files/board/16c3a644-ec6f-476b-a38f-3e1bb05e9722.pdf</pdfUrl></item><item><type>현지조사</type><codeNo>W_F_024</codeNo><category>민담</category><category2>MYTH2.016</category2><ebook>W_F_024</ebook><ebookUrl>http://www.jeju.go.kr/pub/site/cul/ebook/003/1928/W_F_024/e-book.html</ebookUrl><title>벡발노인 따라 저승 갓당 온 사름</title><tag>저승,백마,사름,명주,군대,6·25,벡발노인,염녀데왕</tag><pdf>W_F_024.pdf</pdf><pdfUrl>http://www.jeju.go.kr/files/board/0b88bf57-b6ec-4ed6-b078-082b8b5ee051.pdf</pdfUrl></item><item><type>현지조사</type><codeNo>W_F_025</codeNo><category>민담</category><category2>MYTH2.015</category2><ebook>W_F_025</ebook><ebookUrl>http://www.jeju.go.kr/pub/site/cul/ebook/003/1928/W_F_025/e-book.html</ebookUrl><title>복 엇인 푸나무 장사꾼</title><tag>아기,하늘,푸나무,이름,거지,복주는방,두갓이,장사꾼</tag><pdf>W_F_025.pdf</pdf><pdfUrl>http://www.jeju.go.kr/files/board/8b40d028-1846-4da2-a7fa-71b5c4947ec0.pdf</pdfUrl></item><item><type>현지조사</type><codeNo>W_F_026</codeNo><category>민담</category><category2>MYTH2.016</category2><ebook>W_F_026</ebook><ebookUrl>http://www.jeju.go.kr/pub/site/cul/ebook/003/1928/W_F_026/e-book.html</ebookUrl><title>불미귀신 도체비</title><tag>도체비,불미,덕수리,송칩,뒷하르방,김칩,불미귀신,진도벨파진</tag><pdf>W_F_026.pdf</pdf><pdfUrl>http://www.jeju.go.kr/files/board/32c24867-9d6c-4440-95d1-ea49b5e195c5.pdf</pdfUrl></item><item><type>현지조사</type><codeNo>W_F_027</codeNo><category>민담</category><category2>MYTH2.016</category2><ebook>W_F_027</ebook><ebookUrl>http://www.jeju.go.kr/pub/site/cul/ebook/003/1928/W_F_027/e-book.html</ebookUrl><title>비 오면 나타나는 기신세</title><tag>비,구신,기신세,구좌읍하도리</tag><pdf>W_F_027.pdf</pdf><pdfUrl>http://www.jeju.go.kr/files/board/1ea17210-dd84-479e-9302-5dd95f918670.pdf</pdfUrl></item><item><type>현지조사</type><codeNo>W_F_028</codeNo><category>민담</category><category2>MYTH2.016</category2><ebook>W_F_028</ebook><ebookUrl>http://www.jeju.go.kr/pub/site/cul/ebook/003/1928/W_F_028/e-book.html</ebookUrl><title>사름 *놀 피 내오민 엇어지는 도체비</title><tag>도체비,도체빗불,사름,원당봉,웬당,벌랑벌랑,등알등알,진드르</tag><pdf>W_F_028.pdf</pdf><pdfUrl>http://www.jeju.go.kr/files/board/401db3c1-dabd-4427-a3ab-a8c181f5f6f8.pdf</pdfUrl></item><item><type>현지조사</type><codeNo>W_F_029</codeNo><category>민담</category><category2>MYTH2.016</category2><ebook>W_F_029</ebook><ebookUrl>http://www.jeju.go.kr/pub/site/cul/ebook/003/1928/W_F_029/e-book.html</ebookUrl><title>사름 홀리는 도체비</title><tag>도체비,하르방,처녀,헛게,사름,헛게비,구좌읍세화리</tag><pdf>W_F_029.pdf</pdf><pdfUrl>http://www.jeju.go.kr/files/board/bbcb66bd-0f96-4542-9e73-bbb9bd5b9b1b.pdf</pdfUrl></item><item><type>현지조사</type><codeNo>W_F_030</codeNo><category>민담</category><category2>MYTH2.015</category2><ebook>W_F_030</ebook><ebookUrl>http://www.jeju.go.kr/pub/site/cul/ebook/003/1928/W_F_030/e-book.html</ebookUrl><title>살인 누명 벗은 주인</title><tag>과거,주인,살인,막살이,누명</tag><pdf>W_F_030.pdf</pdf><pdfUrl>http://www.jeju.go.kr/files/board/0a5eaa74-3e5f-4987-811f-c81b35e8a5d2.pdf</pdfUrl></item><item><type>현지조사</type><codeNo>W_F_031</codeNo><category>민담</category><category2>MYTH2.016</category2><ebook>W_F_031</ebook><ebookUrl>http://www.jeju.go.kr/pub/site/cul/ebook/003/1928/W_F_031/e-book.html</ebookUrl><title>소곰밧 귀신</title><tag>귀신,구신,진새미골,소곰밧,염밧,귀신새</tag><pdf>W_F_031.pdf</pdf><pdfUrl>http://www.jeju.go.kr/files/board/b92d07a2-9050-49b8-9fa3-9f3b36c3a993.pdf</pdfUrl></item><item><type>현지조사</type><codeNo>W_F_032</codeNo><category>민담</category><category2>MYTH2.016</category2><ebook>W_F_032</ebook><ebookUrl>http://www.jeju.go.kr/pub/site/cul/ebook/003/1928/W_F_032/e-book.html</ebookUrl><title>소곰밧 헛게</title><tag>도체비,귀신,헛게,귀신대,노래부르는소리,아이우는소리,소곰밧,기신새,헛불,다리벌리기,사흘내에죽음</tag><pdf>W_F_032.pdf</pdf><pdfUrl>http://www.jeju.go.kr/files/board/025e306c-0efd-4f3b-b367-48418b950b83.pdf</pdfUrl></item><item><type>현지조사</type><codeNo>W_F_033</codeNo><category>민담</category><category2>MYTH2.017</category2><ebook>W_F_033</ebook><ebookUrl>http://www.jeju.go.kr/pub/site/cul/ebook/003/1928/W_F_033/e-book.html</ebookUrl><title>솟 우에 앚인 문어</title><tag>구신,구덕,솟,구좌읍세화리,문어,갯것이</tag><pdf>W_F_033.pdf</pdf><pdfUrl>http://www.jeju.go.kr/files/board/c57d1326-8bcc-4bdc-bc5a-02cf9159381e.pdf</pdfUrl></item><item><type>현지조사</type><codeNo>W_F_034</codeNo><category>민담</category><category2>MYTH2.016</category2><ebook>W_F_034</ebook><ebookUrl>http://www.jeju.go.kr/pub/site/cul/ebook/003/1928/W_F_034/e-book.html</ebookUrl><title>솟강알에 불 부찐 도체비</title><tag>도체비,불,정심,솟강알</tag><pdf>W_F_034.pdf</pdf><pdfUrl>http://www.jeju.go.kr/files/board/574f1b82-6e64-4388-b7a1-490ebc318fb2.pdf</pdfUrl></item><item><type>현지조사</type><codeNo>W_F_035</codeNo><category>민담</category><category2>MYTH2.016</category2><ebook>W_F_035</ebook><ebookUrl>http://www.jeju.go.kr/pub/site/cul/ebook/003/1928/W_F_035/e-book.html</ebookUrl><title>쉐뿔에 쳐 죽을 운</title><tag>스님,팡돌,권제,쉐뿔,죽을운,귓밥,운</tag><pdf>W_F_035.pdf</pdf><pdfUrl>http://www.jeju.go.kr/files/board/b46176dd-a6ef-41ef-b61e-08bdace72efe.pdf</pdfUrl></item><item><type>현지조사</type><codeNo>W_F_036</codeNo><category>민담</category><category2>MYTH2.016</category2><ebook>W_F_036</ebook><ebookUrl>http://www.jeju.go.kr/pub/site/cul/ebook/003/1928/W_F_036/e-book.html</ebookUrl><title>식게칩이 구신</title><tag>구신,살인,성산리,식게칩,차</tag><pdf>W_F_036.pdf</pdf><pdfUrl>http://www.jeju.go.kr/files/board/ff3ea920-03dc-4fb2-98f0-1660f1938ed1.pdf</pdfUrl></item><item><type>현지조사</type><codeNo>W_F_037</codeNo><category>민담</category><category2>MYTH2.015</category2><ebook>W_F_037</ebook><ebookUrl>http://www.jeju.go.kr/pub/site/cul/ebook/003/1928/W_F_037/e-book.html</ebookUrl><title>식겟날 큰 비 오는 집</title><tag>비,제사,집,정시,식게,방에,이칩이,불난집,기와집,방에트는집,큰비,식겟날</tag><pdf>W_F_037.pdf</pdf><pdfUrl>http://www.jeju.go.kr/files/board/dc414eba-ef3c-48d6-b228-83716a9618a7.pdf</pdfUrl></item><item><type>현지조사</type><codeNo>W_F_038</codeNo><category>민담</category><category2>MYTH2.015</category2><ebook>W_F_038</ebook><ebookUrl>http://www.jeju.go.kr/pub/site/cul/ebook/003/1928/W_F_038/e-book.html</ebookUrl><title>아기업게 말도 들으라</title><tag>말,김통정,장수물,토성,아기업게,안개,문,휏부리,몽고,구싯물,모기</tag><pdf>W_F_038.pdf</pdf><pdfUrl>http://www.jeju.go.kr/files/board/8c10b9ce-ee67-4b99-a48d-212e7d4c6715.pdf</pdfUrl></item><item><type>현지조사</type><codeNo>W_F_039</codeNo><category>민담</category><category2>MYTH2.016</category2><ebook>W_F_039</ebook><ebookUrl>http://www.jeju.go.kr/pub/site/cul/ebook/003/1928/W_F_039/e-book.html</ebookUrl><title>애기무덤에서 나는 우는 소리</title><tag>도체빗불,우는소리,펀즉펀즉,애기무덤</tag><pdf>W_F_039.pdf</pdf><pdfUrl>http://www.jeju.go.kr/files/board/22a7c745-6c41-4328-bc09-7f92db1fde59.pdf</pdfUrl></item><item><type>현지조사</type><codeNo>W_F_040</codeNo><category>민담</category><category2>MYTH2.015</category2><ebook>W_F_040</ebook><ebookUrl>http://www.jeju.go.kr/pub/site/cul/ebook/003/1928/W_F_040/e-book.html</ebookUrl><title>여우누이와 오빠</title><tag>여우,간,호랑이,오누이,오빠,대왓,쳉빗,펭,물바다</tag><pdf>W_F_040.pdf</pdf><pdfUrl>http://www.jeju.go.kr/files/board/c1ef34d8-0948-49a0-b72e-91b0f28ca567.pdf</pdfUrl></item><item><type>현지조사</type><codeNo>W_F_041</codeNo><category>민담</category><category2>MYTH2.016</category2><ebook>W_F_041</ebook><ebookUrl>http://www.jeju.go.kr/pub/site/cul/ebook/003/1928/W_F_041/e-book.html</ebookUrl><title>여자로 둔갑한 샘물의 도체비</title><tag>도체비,여자,샘물,둔갑,묵은도남,새벡</tag><pdf>W_F_041.pdf</pdf><pdfUrl>http://www.jeju.go.kr/files/board/7104f727-9ec9-4afd-93b3-d8c0339aa2a4.pdf</pdfUrl></item><item><type>현지조사</type><codeNo>W_F_042</codeNo><category>민담</category><category2>MYTH2.016</category2><ebook>W_F_042</ebook><ebookUrl>http://www.jeju.go.kr/pub/site/cul/ebook/003/1928/W_F_042/e-book.html</ebookUrl><title>오설룡*또님아기</title><tag>소,말,간,철갈이,구좌읍하도리,오설룡따님아기</tag><pdf>W_F_042.pdf</pdf><pdfUrl>http://www.jeju.go.kr/files/board/69c4615a-b7f9-4e40-85c0-ef0dd92d94c5.pdf</pdfUrl></item><item><type>현지조사</type><codeNo>W_F_043</codeNo><category>민담</category><category2>MYTH2.016</category2><ebook>W_F_043</ebook><ebookUrl>http://www.jeju.go.kr/pub/site/cul/ebook/003/1928/W_F_043/e-book.html</ebookUrl><title>올레서 만난 기신세</title><tag>할망,심방,종달리,올레,기신세,학교,세밧디할망</tag><pdf>W_F_043.pdf</pdf><pdfUrl>http://www.jeju.go.kr/files/board/6dfcb841-ebf3-4603-81a8-7a1978f896d3.pdf</pdfUrl></item><item><type>현지조사</type><codeNo>W_F_044</codeNo><category>민담</category><category2>MYTH2.015</category2><ebook>W_F_044</ebook><ebookUrl>http://www.jeju.go.kr/pub/site/cul/ebook/003/1928/W_F_044/e-book.html</ebookUrl><title>왕의 후사가 뒌 영의정의 아들</title><tag>아들,왕,후사,영의정,중국사신,새끼벤우메</tag><pdf>W_F_044.pdf</pdf><pdfUrl>http://www.jeju.go.kr/files/board/80ad611b-3ec7-486d-90d1-58b15634b3b9.pdf</pdfUrl></item><item><type>현지조사</type><codeNo>W_F_045</codeNo><category>민담</category><category2>MYTH2.017</category2><ebook>W_F_045</ebook><ebookUrl>http://www.jeju.go.kr/pub/site/cul/ebook/003/1928/W_F_045/e-book.html</ebookUrl><title>우스갯소리</title><tag>하르방,불,거짓말,우스갯소리,송아기,궤기장시</tag><pdf>W_F_045.pdf</pdf><pdfUrl>http://www.jeju.go.kr/files/board/20b16635-99ab-492a-bbf3-4235911aae6e.pdf</pdfUrl></item><item><type>현지조사</type><codeNo>W_F_046</codeNo><category>민담</category><category2>MYTH2.015</category2><ebook>W_F_046</ebook><ebookUrl>http://www.jeju.go.kr/pub/site/cul/ebook/003/1928/W_F_046/e-book.html</ebookUrl><title>위기 면한 강소은</title><tag>쇠,지혜,강소은,궷물,볏,위기</tag><pdf>W_F_046.pdf</pdf><pdfUrl>http://www.jeju.go.kr/files/board/bceb2203-0499-479e-864f-0319ca670044.pdf</pdfUrl></item><item><type>현지조사</type><codeNo>W_F_048</codeNo><category>민담</category><category2>MYTH2.016</category2><ebook>W_F_048</ebook><ebookUrl>http://www.jeju.go.kr/pub/site/cul/ebook/003/1928/W_F_048/e-book.html</ebookUrl><title>저승 다녀온 명월리 할망</title><tag>물,할망,다리,저승,명월리,한림읍명월리,관,미녕,두루메기,꼿밧,히얀강아지</tag><pdf>W_F_048.pdf</pdf><pdfUrl>http://www.jeju.go.kr/files/board/fc9d9f07-601d-46d1-9b8e-a158e683d845.pdf</pdfUrl></item><item><type>현지조사</type><codeNo>W_F_049</codeNo><category>민담</category><category2>MYTH2.016</category2><ebook>W_F_049</ebook><ebookUrl>http://www.jeju.go.kr/pub/site/cul/ebook/003/1928/W_F_049/e-book.html</ebookUrl><title>저승 다녀온 우도 할망</title><tag>할망,저승,꿈,우도,재산,우도할망</tag><pdf>W_F_049.pdf</pdf><pdfUrl>http://www.jeju.go.kr/files/board/de832b4c-bb45-461d-bfda-5217306360af.pdf</pdfUrl></item><item><type>현지조사</type><codeNo>W_F_050</codeNo><category>민담</category><category2>MYTH2.016</category2><ebook>W_F_050</ebook><ebookUrl>http://www.jeju.go.kr/pub/site/cul/ebook/003/1928/W_F_050/e-book.html</ebookUrl><title>저싱 사흘 이싱 삼십년</title><tag>하르방,처녀,부자,구좌읍종달리,저싱,이싱,저싱창고,삼십년</tag><pdf>W_F_050.pdf</pdf><pdfUrl>http://www.jeju.go.kr/files/board/b50b451c-c2c3-4c03-ad4b-3803706b5bfb.pdf</pdfUrl></item><item><type>현지조사</type><codeNo>W_F_051</codeNo><category>민담</category><category2>MYTH2.014</category2><ebook>W_F_051</ebook><ebookUrl>http://www.jeju.go.kr/pub/site/cul/ebook/003/1928/W_F_051/e-book.html</ebookUrl><title>적둑베기 일러분 가마귀</title><tag>굿,귀양,가마귀,베엠,하늘옥항,적둑베기,청대산마고할망,대바지</tag><pdf>W_F_051.pdf</pdf><pdfUrl>http://www.jeju.go.kr/files/board/7e7c4106-4883-4840-b365-a396d85804de.pdf</pdfUrl></item><item><type>현지조사</type><codeNo>W_F_052</codeNo><category>민담</category><category2>MYTH2.016</category2><ebook>W_F_052</ebook><ebookUrl>http://www.jeju.go.kr/pub/site/cul/ebook/003/1928/W_F_052/e-book.html</ebookUrl><title>전생 업보로 만난 남편</title><tag>스님,남편,절,시주,두부부,전생,셋단,미륵부처,인과응보,설법,업보</tag><pdf>W_F_052.pdf</pdf><pdfUrl>http://www.jeju.go.kr/files/board/d544983a-0c29-4355-926e-60bec63ab425.pdf</pdfUrl></item><item><type>현지조사</type><codeNo>W_F_053</codeNo><category>민담</category><category2>MYTH2.016</category2><ebook>W_F_053</ebook><ebookUrl>http://www.jeju.go.kr/pub/site/cul/ebook/003/1928/W_F_053/e-book.html</ebookUrl><title>젊은 남자로 둔갑헌 도체비</title><tag>도체비,굿,둔갑,넋드림,젊은남자,축축헌날,애월읍광령리</tag><pdf>W_F_053.pdf</pdf><pdfUrl>http://www.jeju.go.kr/files/board/797ddeae-68fe-4d86-a468-c23b3afc75cc.pdf</pdfUrl></item><item><type>현지조사</type><codeNo>W_F_054</codeNo><category>민담</category><category2>MYTH2.015</category2><ebook>W_F_054</ebook><ebookUrl>http://www.jeju.go.kr/pub/site/cul/ebook/003/1928/W_F_054/e-book.html</ebookUrl><title>족은*똘과 마퉁이</title><tag>딸,마퉁이,복,마,금,거러지잔치,베또롱아래선그믓</tag><pdf>W_F_054.pdf</pdf><pdfUrl>http://www.jeju.go.kr/files/board/bc386aca-6a9d-4698-862c-deabab16b03a.pdf</pdfUrl></item><item><type>현지조사</type><codeNo>W_F_055</codeNo><category>민담</category><category2>MYTH2.015</category2><ebook>W_F_055</ebook><ebookUrl>http://www.jeju.go.kr/pub/site/cul/ebook/003/1928/W_F_055/e-book.html</ebookUrl><title>지붕우티 하르방</title><tag>힘,하르방,할망,지붕,호박</tag><pdf>W_F_055.pdf</pdf><pdfUrl>http://www.jeju.go.kr/files/board/f8b6a8d2-0dea-4a71-80ff-7b34536050ef.pdf</pdfUrl></item><item><type>현지조사</type><codeNo>W_F_056</codeNo><category>민담</category><category2>MYTH2.015</category2><ebook>W_F_056</ebook><ebookUrl>http://www.jeju.go.kr/pub/site/cul/ebook/003/1928/W_F_056/e-book.html</ebookUrl><title>청나라 황제가 된 부씨</title><tag>발복,부씨,산소,왕후지지,황제,청나라황제,삼대적선,보자꾼,청나라</tag><pdf>W_F_056.pdf</pdf><pdfUrl>http://www.jeju.go.kr/files/board/b56762df-f69d-4b55-aa83-a4d92d501c23.pdf</pdfUrl></item><item><type>현지조사</type><codeNo>W_F_057</codeNo><category>민담</category><category2>MYTH2.015</category2><ebook>W_F_057</ebook><ebookUrl>http://www.jeju.go.kr/pub/site/cul/ebook/003/1928/W_F_057/e-book.html</ebookUrl><title>콩데기 *폿데기</title><tag>콩데기,항아리,새,팟데기,두꺼비,콩주,신한짝,꽃신</tag><pdf>W_F_057.pdf</pdf><pdfUrl>http://www.jeju.go.kr/files/board/2ebd4f13-c3a6-4cd2-abd1-53fed3c04fb3.pdf</pdfUrl></item><item><type>현지조사</type><codeNo>W_F_058</codeNo><category>민담</category><category2>MYTH2.015</category2><ebook>W_F_058</ebook><ebookUrl>http://www.jeju.go.kr/pub/site/cul/ebook/003/1928/W_F_058/e-book.html</ebookUrl><title>콩데기영 *폿데기영</title><tag>물,콩데기,콩,가마귀,팟데기,항,예펜</tag><pdf>W_F_058.pdf</pdf><pdfUrl>http://www.jeju.go.kr/files/board/65ca6561-fda8-45b4-9df5-cabfedc988aa.pdf</pdfUrl></item><item><type>현지조사</type><codeNo>W_F_059</codeNo><category>민담</category><category2>MYTH2.015</category2><ebook>W_F_059</ebook><ebookUrl>http://www.jeju.go.kr/pub/site/cul/ebook/003/1928/W_F_059/e-book.html</ebookUrl><title>콩씨애기 *폿씨애기</title><tag>환생,다슴애기,팟데기,콩씨</tag><pdf>W_F_059.pdf</pdf><pdfUrl>http://www.jeju.go.kr/files/board/35c1f3b2-ec37-443d-9bee-abd56d1cad75.pdf</pdfUrl></item><item><type>현지조사</type><codeNo>W_F_060</codeNo><category>민담</category><category2>MYTH2.016</category2><ebook>W_F_060</ebook><ebookUrl>http://www.jeju.go.kr/pub/site/cul/ebook/003/1928/W_F_060/e-book.html</ebookUrl><title>파랑한 도체빗불</title><tag>도체비,도체빗불,소곰막,벨롱벨롱,비추기,파랑한불,파랑</tag><pdf>W_F_060.pdf</pdf><pdfUrl>http://www.jeju.go.kr/files/board/d3d78218-7ccf-4433-9024-eb7fbe0b5e13.pdf</pdfUrl></item><item><type>현지조사</type><codeNo>W_F_061</codeNo><category>민담</category><category2>MYTH2.014</category2><ebook>W_F_061</ebook><ebookUrl>http://www.jeju.go.kr/pub/site/cul/ebook/003/1928/W_F_061/e-book.html</ebookUrl><title>폿(*)버렝이</title><tag>부자,하늘항제,고린장</tag><pdf>W_F_061.pdf</pdf><pdfUrl>http://www.jeju.go.kr/files/board/8d1da27a-5b4a-4fa2-808c-05b013241837.pdf</pdfUrl></item><item><type>현지조사</type><codeNo>W_F_062</codeNo><category>민담</category><category2>MYTH2.016</category2><ebook>W_F_062</ebook><ebookUrl>http://www.jeju.go.kr/pub/site/cul/ebook/003/1928/W_F_062/e-book.html</ebookUrl><title>한복 입은 여자로 둔갑헌 도깨비</title><tag>도깨비,여자,구신,둔갑,한복,부칩</tag><pdf>W_F_062.pdf</pdf><pdfUrl>http://www.jeju.go.kr/files/board/a771b864-ff95-44ac-8950-a7ac269af750.pdf</pdfUrl></item><item><type>현지조사</type><codeNo>W_F_063</codeNo><category>민담</category><category2>MYTH2.015</category2><ebook>W_F_063</ebook><ebookUrl>http://www.jeju.go.kr/pub/site/cul/ebook/003/1928/W_F_063/e-book.html</ebookUrl><title>해와 *돌이 뒌 오누이</title><tag>제사,구신,오누이,달,해</tag><pdf>W_F_063.pdf</pdf><pdfUrl>http://www.jeju.go.kr/files/board/29102417-7915-4266-9ed4-47bb61d8393e.pdf</pdfUrl></item><item><type>현지조사</type><codeNo>W_F_064</codeNo><category>민담</category><category2>MYTH2.016</category2><ebook>W_F_064</ebook><ebookUrl>http://www.jeju.go.kr/pub/site/cul/ebook/003/1928/W_F_064/e-book.html</ebookUrl><title>헛게 *또라 간 사름</title><tag>헛게,사름,세화리,손당,덤불</tag><pdf>W_F_064.pdf</pdf><pdfUrl>http://www.jeju.go.kr/files/board/4f9dd343-527d-4055-b6be-c9d8bfcc8f9f.pdf</pdfUrl></item><item><type>현지조사</type><codeNo>W_F_065</codeNo><category>민담</category><category2>MYTH2.016</category2><ebook>W_F_065</ebook><ebookUrl>http://www.jeju.go.kr/pub/site/cul/ebook/003/1928/W_F_065/e-book.html</ebookUrl><title>헛게 소리</title><tag>노래부르는소리,아이우는소리,솟곰밧,헛게소리,헛소리</tag><pdf>W_F_065.pdf</pdf><pdfUrl>http://www.jeju.go.kr/files/board/242b37f8-4b6b-470b-895c-55f2ce280d5d.pdf</pdfUrl></item><item><type>현지조사</type><codeNo>W_F_066</codeNo><category>민담</category><category2>MYTH2.015</category2><ebook>W_F_066</ebook><ebookUrl>http://www.jeju.go.kr/pub/site/cul/ebook/003/1928/W_F_066/e-book.html</ebookUrl><title>호랑이와 해님 달님</title><tag>호랑이,떡,연못,밧줄,해님,달님,닷줄</tag><pdf>W_F_066.pdf</pdf><pdfUrl>http://www.jeju.go.kr/files/board/d9da4f34-1bf0-4e14-929f-4f05a5672489.pdf</pdfUrl></item><item><type>현지조사</type><codeNo>W_F_067</codeNo><category>민담</category><category2>MYTH2.015</category2><ebook>W_F_067</ebook><ebookUrl>http://www.jeju.go.kr/pub/site/cul/ebook/003/1928/W_F_067/e-book.html</ebookUrl><title>힘쎈 벤할망</title><tag>힘,소,성읍리,벤할망,석전,정의헹교</tag><pdf>W_F_067.pdf</pdf><pdfUrl>http://www.jeju.go.kr/files/board/5533a85d-c0b9-4286-9271-142e06cba42b.pdf</pdfUrl></item><item><type>현지조사</type><codeNo>W_F_068</codeNo><category>민담</category><category2>MYTH2.015</category2><ebook>W_F_068</ebook><ebookUrl>http://www.jeju.go.kr/pub/site/cul/ebook/003/1928/W_F_068/e-book.html</ebookUrl><title>힘쎈 할망</title><tag>힘,하르방,할망,지붕,호박</tag><pdf>W_F_068.pdf</pdf><pdfUrl>http://www.jeju.go.kr/files/board/0bf7eedf-8aae-40e9-b509-1a107b1662b1.pdf</pdfUrl></item><item><type>해제</type><codeNo>C_F_001</codeNo><category>민담</category><category2>MYTH2.014</category2><ebook>C_F_001</ebook><ebookUrl>http://www.jeju.go.kr/pub/site/cul/ebook/002/1928/C_F_001/e-book.html</ebookUrl><title>개와 닭의 원한</title><tag>개,닭,사굴(뱀굴),사왕,삼해유,계불과삼년,구불과칠년,원한</tag><pdf>C_F_001.pdf</pdf><pdfUrl>http://www.jeju.go.kr/files/board/55a8aded-3aef-4721-ae99-2635cd721389.pdf</pdfUrl></item><item><type>해제</type><codeNo>C_F_002</codeNo><category>민담</category><category2>MYTH2.015</category2><ebook>C_F_002</ebook><ebookUrl>http://www.jeju.go.kr/pub/site/cul/ebook/002/1928/C_F_002/e-book.html</ebookUrl><title>겸손을 배운 제자</title><tag>여자,부인,제자,겸손,비문,소학교,태학관,성균관,선생님,아버님</tag><pdf>C_F_002.pdf</pdf><pdfUrl>http://www.jeju.go.kr/files/board/ba30981e-d24d-4d07-b5ee-b1b66e3070f2.pdf</pdfUrl></item><item><type>해제</type><codeNo>C_F_003</codeNo><category>민담</category><category2>MYTH2.015</category2><ebook>C_F_003</ebook><ebookUrl>http://www.jeju.go.kr/pub/site/cul/ebook/002/1928/C_F_003/e-book.html</ebookUrl><title>계모의 모략(1)</title><tag>족은각시,어머니,큰아들,계모,족은어멍,신랑,신부,점쟁이,모략,후처,치마폭</tag><pdf>C_F_003.pdf</pdf><pdfUrl>http://www.jeju.go.kr/files/board/de70aa6a-fa64-4485-8944-7aa9c287eee0.pdf</pdfUrl></item><item><type>해제</type><codeNo>C_F_004</codeNo><category>민담</category><category2>MYTH2.015</category2><ebook>C_F_004</ebook><ebookUrl>http://www.jeju.go.kr/pub/site/cul/ebook/002/1928/C_F_004/e-book.html</ebookUrl><title>과거보는 선비 이야기</title><tag>과거,신선,선비,특과,낙방,어떤노인,매연,어떤선비,시골말</tag><pdf>C_F_004.pdf</pdf><pdfUrl>http://www.jeju.go.kr/files/board/045ec4f5-e9ca-4660-be0a-8d9b3f07ede0.pdf</pdfUrl></item><item><type>해제</type><codeNo>C_F_005</codeNo><category>민담</category><category2>MYTH2.015</category2><ebook>C_F_005</ebook><ebookUrl>http://www.jeju.go.kr/pub/site/cul/ebook/002/1928/C_F_005/e-book.html</ebookUrl><title>괴상한 세 동무</title><tag>각시,스님,가마귀,관상,동무,짐승,음식맛,제비,밥상,대축술,재판장,천리터</tag><pdf>C_F_005.pdf</pdf><pdfUrl>http://www.jeju.go.kr/files/board/e7da1f40-b774-409d-b6d7-43b945302bf5.pdf</pdfUrl></item><item><type>해제</type><codeNo>C_F_006</codeNo><category>민담</category><category2>MYTH2.015</category2><ebook>C_F_006</ebook><ebookUrl>http://www.jeju.go.kr/pub/site/cul/ebook/002/1928/C_F_006/e-book.html</ebookUrl><title>구렁이가 된 막내</title><tag>하르방,구렁이,삼형제,신선,막내,도학,셋놈,삼성제,평양감사,동삼,서문,복숭아,큰형,세형제</tag><pdf>C_F_006.pdf</pdf><pdfUrl>http://www.jeju.go.kr/files/board/09083e50-b805-459d-bce7-bc51086486af.pdf</pdfUrl></item><item><type>해제</type><codeNo>C_F_007</codeNo><category>민담</category><category2>MYTH2.016</category2><ebook>C_F_007</ebook><ebookUrl>http://www.jeju.go.kr/pub/site/cul/ebook/002/1928/C_F_007/e-book.html</ebookUrl><title>귀신대2</title><tag>심방,귀신대,돌가루,푸다시,전봇대,귀신대2</tag><pdf>C_F_007.pdf</pdf><pdfUrl>http://www.jeju.go.kr/files/board/dd51b7a6-d286-4b4d-91b7-aebd5a44c302.pdf</pdfUrl></item><item><type>해제</type><codeNo>C_F_008</codeNo><category>민담</category><category2>MYTH2.015</category2><ebook>C_F_008</ebook><ebookUrl>http://www.jeju.go.kr/pub/site/cul/ebook/002/1928/C_F_008/e-book.html</ebookUrl><title>말 한마디로 복 얻은 노인</title><tag>말,사또,도둑,노인,초신,복,엄부럭총각,서른냥,돈전대,말한마디</tag><pdf>C_F_008.pdf</pdf><pdfUrl>http://www.jeju.go.kr/files/board/dfe933dd-4c76-4f07-8215-01b31e2a1d18.pdf</pdfUrl></item><item><type>해제</type><codeNo>C_F_009</codeNo><category>민담</category><category2>MYTH2.014</category2><ebook>C_F_009</ebook><ebookUrl>http://www.jeju.go.kr/pub/site/cul/ebook/002/1928/C_F_009/e-book.html</ebookUrl><title>말(馬)이야기</title><tag>말,아들,아버지,향교,두모리,수원리,상제,방장대,허제비</tag><pdf>C_F_009.pdf</pdf><pdfUrl>http://www.jeju.go.kr/files/board/e2cba13a-233f-47ca-80a5-e08c4aebfe73.pdf</pdfUrl></item><item><type>해제</type><codeNo>C_F_010</codeNo><category>민담</category><category2>MYTH2.016</category2><ebook>C_F_010</ebook><ebookUrl>http://www.jeju.go.kr/pub/site/cul/ebook/002/1928/C_F_010/e-book.html</ebookUrl><title>멜잡는 도채비</title><tag>도깨비,도채비,멜,제물,멸치,영감,한동,계장,공원,응감,대축(옥수수),범벅,오메기떡,멸치어장</tag><pdf>C_F_010.pdf</pdf><pdfUrl>http://www.jeju.go.kr/files/board/876e34d4-9e6a-48c0-a4e2-1174ce4de037.pdf</pdfUrl></item><item><type>해제</type><codeNo>C_F_011</codeNo><category>민담</category><category2>MYTH2.015</category2><ebook>C_F_011</ebook><ebookUrl>http://www.jeju.go.kr/pub/site/cul/ebook/002/1928/C_F_011/e-book.html</ebookUrl><title>사름 아니라는 욕</title><tag>사름,이계징,이락당,욕,도련동</tag><pdf>C_F_011.pdf</pdf><pdfUrl>http://www.jeju.go.kr/files/board/ed700bd7-88bb-418e-9cda-7442d03e2cb8.pdf</pdfUrl></item><item><type>해제</type><codeNo>C_F_012</codeNo><category>민담</category><category2>MYTH2.016</category2><ebook>C_F_012</ebook><ebookUrl>http://www.jeju.go.kr/pub/site/cul/ebook/002/1928/C_F_012/e-book.html</ebookUrl><title>산도채비</title><tag>관덕정,도채비,주인,산도채비,죽은도채비</tag><pdf>C_F_012.pdf</pdf><pdfUrl>http://www.jeju.go.kr/files/board/5c79a088-c36f-4f00-b1d3-c393caf3e44e.pdf</pdfUrl></item><item><type>해제</type><codeNo>C_F_013</codeNo><category>민담</category><category2>MYTH2.014</category2><ebook>C_F_013</ebook><ebookUrl>http://www.jeju.go.kr/pub/site/cul/ebook/002/1928/C_F_013/e-book.html</ebookUrl><title>신기한 호랑이 눈썹</title><tag>각시,팥죽,호랑이,사람,눈썹,서월,푸나무장시,아기덜,심바람(심부름)</tag><pdf>C_F_013.pdf</pdf><pdfUrl>http://www.jeju.go.kr/files/board/b6e07b9e-1a90-4f43-92d9-7adf23838d8f.pdf</pdfUrl></item><item><type>현지조사</type><codeNo>W-F-202</codeNo><category>민담</category><category2>MYTH2.016</category2><ebook>W_F_202</ebook><ebookUrl>http://www.jeju.go.kr/pub/site/cul/ebook/003/1928/W_F_202/e-book.html</ebookUrl><title>공서방과 배서방</title><tag>어머니,공서방,하님,배서방,공가</tag><pdf>W_F_202.pdf</pdf><pdfUrl>http://www.jeju.go.kr/files/board/9abd74a5-5197-4948-a1e4-33b9822e4287.pdf</pdfUrl></item><item><type>현지조사</type><codeNo>W-F-203</codeNo><category>민담</category><category2>MYTH2.016</category2><ebook>W_F_203</ebook><ebookUrl>http://www.jeju.go.kr/pub/site/cul/ebook/003/1928/W_F_203/e-book.html</ebookUrl><title>귀신 말 들은 걸바시 부부</title><tag>귀신,제사,김녕리,식게,북촌리,산담,돌화로,걸바시,동녕</tag><pdf>W_F_203.pdf</pdf><pdfUrl>http://www.jeju.go.kr/files/board/55fc8026-b222-4892-aa74-bb52579fe638.pdf</pdfUrl></item><item><type>현지조사</type><codeNo>W-F-204</codeNo><category>민담</category><category2>MYTH2.016</category2><ebook>W_F_204</ebook><ebookUrl>http://www.jeju.go.kr/pub/site/cul/ebook/003/1928/W_F_204/e-book.html</ebookUrl><title>그슨새</title><tag>땅,죽음,그슨새,거멍한것</tag><pdf>W_F_204.pdf</pdf><pdfUrl>http://www.jeju.go.kr/files/board/e8b944d4-fba8-4181-aa98-dc0a767016ed.pdf</pdfUrl></item><item><type>현지조사</type><codeNo>W-F-205</codeNo><category>민담</category><category2>MYTH2.015</category2><ebook>W_F_205</ebook><ebookUrl>http://www.jeju.go.kr/pub/site/cul/ebook/003/1928/W_F_205/e-book.html</ebookUrl><title>금송아지</title><tag>아들,족은각시,작은부인,큰부인,큰각시,과거시험,금송아지,셋각시,귀동자환영,양병</tag><pdf>W_F_205.pdf</pdf><pdfUrl>http://www.jeju.go.kr/files/board/66dbaa55-ef55-4378-8e2d-f9a167fac741.pdf</pdfUrl></item><item><type>현지조사</type><codeNo>W-F-206</codeNo><category>민담</category><category2>MYTH2.016</category2><ebook>W_F_206</ebook><ebookUrl>http://www.jeju.go.kr/pub/site/cul/ebook/003/1928/W_F_206/e-book.html</ebookUrl><title>기십 센 여자</title><tag>도체비,도깨비,불,여자,밤,밧,보리,뒷골동산,기십,초롱불</tag><pdf>W_F_206.pdf</pdf><pdfUrl>http://www.jeju.go.kr/files/board/f27f401d-3c9a-4274-8a5b-8c624c8c2b59.pdf</pdfUrl></item><item><type>현지조사</type><codeNo>W-F-207</codeNo><category>민담</category><category2>MYTH2.015</category2><ebook>W_F_207</ebook><ebookUrl>http://www.jeju.go.kr/pub/site/cul/ebook/003/1928/W_F_207/e-book.html</ebookUrl><title>까마귀와 생이가 도와준 콩데기</title><tag>콩데기,항아리,콩,새,까마귀,가마귀,다슴애기,족은어멍,폿,폿데기,생이</tag><pdf>W_F_207.pdf</pdf><pdfUrl>http://www.jeju.go.kr/files/board/52b43151-51ce-4f01-963b-eeaa1c2f09da.pdf</pdfUrl></item><item><type>현지조사</type><codeNo>W-F-208</codeNo><category>민담</category><category2>MYTH2.016</category2><ebook>W_F_208</ebook><ebookUrl>http://www.jeju.go.kr/pub/site/cul/ebook/003/1928/W_F_208/e-book.html</ebookUrl><title>꾀가 많은 토끼</title><tag>하르방,할망,꾀,솟,국,산토끼,물애기</tag><pdf>W_F_208.pdf</pdf><pdfUrl>http://www.jeju.go.kr/files/board/301af7a3-e70f-49b9-8d1b-6774873f223e.pdf</pdfUrl></item></items><query><pageSize>100</pageSize><page>1</page><rows>325</rows></query></jejunetApi>